{"mc":{
	"body6612_3s":{
		"frameRate":15,
		"frames":[
			{"res":"30001","x":-77,"y":-119},
			{"res":"30002","x":-77,"y":-119},
			{"res":"30003","x":-77,"y":-120},
			{"res":"30004","x":-76,"y":-120},
			{"res":"30005","x":-76,"y":-120},
			{"res":"30006","x":-75,"y":-120},
			{"res":"30007","x":-78,"y":-119},
			{"res":"30008","x":-78,"y":-119}
		]
}},
"res":{
	"30001":{"x":160,"y":156,"w":156,"h":152},
	"30002":{"x":2,"y":310,"w":156,"h":152},
	"30003":{"x":2,"y":156,"w":156,"h":152},
	"30004":{"x":316,"y":310,"w":154,"h":152},
	"30005":{"x":160,"y":310,"w":154,"h":152},
	"30006":{"x":318,"y":2,"w":152,"h":152},
	"30007":{"x":160,"y":2,"w":156,"h":152},
	"30008":{"x":2,"y":2,"w":156,"h":152}
}}