{"mc":{
	"body6614_3s":{
		"frameRate":15,
		"frames":[
			{"res":"30001","x":-136,"y":-103},
			{"res":"30002","x":-138,"y":-104},
			{"res":"30003","x":-137,"y":-103},
			{"res":"30004","x":-137,"y":-102},
			{"res":"30005","x":-137,"y":-101},
			{"res":"30006","x":-138,"y":-101},
			{"res":"30007","x":-136,"y":-101},
			{"res":"30008","x":-137,"y":-103}
		]
}},
"res":{
	"30001":{"x":1264,"y":2,"w":178,"h":120},
	"30002":{"x":728,"y":2,"w":178,"h":122},
	"30003":{"x":1086,"y":2,"w":176,"h":122},
	"30004":{"x":908,"y":2,"w":176,"h":122},
	"30005":{"x":548,"y":2,"w":178,"h":122},
	"30006":{"x":366,"y":2,"w":180,"h":122},
	"30007":{"x":184,"y":2,"w":180,"h":122},
	"30008":{"x":2,"y":2,"w":180,"h":122}
}}