{"mc":{
	"hero1011_2a":{
		"frameRate":14,
		"frames":[
			{"res":"20015","x":-62,"y":-104},
			{"res":"20016","x":-62,"y":-94},
			{"res":"20017","x":-79,"y":-92},
			{"res":"20018","x":-75,"y":-109},
			{"res":"20019","x":-65,"y":-107},
			{"res":"20020","x":-48,"y":-101},
			{"res":"20021","x":-47,"y":-113}
		]
}},
"res":{
	"20015":{"x":266,"y":2,"w":132,"h":154},
	"20016":{"x":650,"y":2,"w":136,"h":140},
	"20017":{"x":788,"y":2,"w":140,"h":130},
	"20018":{"x":124,"y":2,"w":140,"h":158},
	"20019":{"x":400,"y":2,"w":128,"h":154},
	"20020":{"x":530,"y":2,"w":118,"h":150},
	"20021":{"x":2,"y":2,"w":120,"h":174}
}}