{"mc":{
	"900009_1r":{
		"frameRate":14,
		"frames":[
			{"res":"10005","x":-60,"y":-88},
			{"res":"10006","x":-56,"y":-89},
			{"res":"10007","x":-60,"y":-89},
			{"res":"10008","x":-64,"y":-83},
			{"res":"10009","x":-72,"y":-84},
			{"res":"10010","x":-65,"y":-86},
			{"res":"10011","x":-66,"y":-87},
			{"res":"10012","x":-69,"y":-89}
		]
}},
"res":{
	"10005":{"x":2,"y":496,"w":106,"h":116},
	"10006":{"x":2,"y":734,"w":104,"h":116},
	"10007":{"x":2,"y":2,"w":110,"h":126},
	"10008":{"x":2,"y":250,"w":106,"h":122},
	"10009":{"x":2,"y":130,"w":108,"h":118},
	"10010":{"x":2,"y":852,"w":102,"h":120},
	"10011":{"x":2,"y":614,"w":104,"h":118},
	"10012":{"x":2,"y":374,"w":106,"h":120}
}}