{"mc":{
	"monster10030_3r":{
		"frameRate":12,
		"frames":[
			{"res":"30006","x":-60,"y":-129},
			{"res":"30007","x":-53,"y":-138},
			{"res":"30008","x":-31,"y":-99},
			{"res":"30009","x":-35,"y":-108},
			{"res":"30010","x":-37,"y":-99},
			{"res":"30011","x":-61,"y":-97}
		]
}},
"res":{
	"30006":{"x":115,"y":0,"w":93,"h":119},
	"30007":{"x":0,"y":0,"w":113,"h":120},
	"30008":{"x":408,"y":0,"w":60,"h":84},
	"30009":{"x":339,"y":83,"w":56,"h":81},
	"30010":{"x":339,"y":0,"w":67,"h":81},
	"30011":{"x":210,"y":0,"w":127,"h":87}
}}