{"mc":{
	"monster20029_2r":{
		"frameRate":12,
		"frames":[
			{"res":"20006","x":-107,"y":-117},
			{"res":"20007","x":-104,"y":-116},
			{"res":"20008","x":-107,"y":-117},
			{"res":"20009","x":-99,"y":-119},
			{"res":"20010","x":-94,"y":-118},
			{"res":"20011","x":-99,"y":-117}
		]
}},
"res":{
	"20006":{"x":0,"y":0,"w":196,"h":124},
	"20007":{"x":0,"y":126,"w":182,"h":120},
	"20008":{"x":184,"y":127,"w":176,"h":122},
	"20009":{"x":0,"y":248,"w":159,"h":128},
	"20010":{"x":161,"y":251,"w":158,"h":126},
	"20011":{"x":198,"y":0,"w":176,"h":125}
}}