{"mc":{
	"monster10013_3r":{
		"frameRate":14,
		"frames":[
			{"res":"30006","x":-41,"y":-89},
			{"res":"30007","x":-43,"y":-85},
			{"res":"30008","x":-35,"y":-92},
			{"res":"30009","x":-36,"y":-89},
			{"res":"30010","x":-40,"y":-82},
			{"res":"30011","x":-38,"y":-89}
		]
}},
"res":{
	"30006":{"x":80,"y":2,"w":80,"h":100},
	"30007":{"x":402,"y":2,"w":84,"h":90},
	"30008":{"x":242,"y":2,"w":76,"h":98},
	"30009":{"x":2,"y":2,"w":76,"h":106},
	"30010":{"x":320,"y":2,"w":80,"h":94},
	"30011":{"x":162,"y":2,"w":78,"h":98}
}}