{"mc":{
	"monster10022_4r":{
		"frameRate":12,
		"frames":[
			{"res":"40006","x":-31,"y":-50},
			{"res":"40007","x":-31,"y":-50},
			{"res":"40008","x":-31,"y":-50},
			{"res":"40009","x":-31,"y":-50},
			{"res":"40010","x":-31,"y":-50},
			{"res":"40011","x":-31,"y":-50}
		]
}},
"res":{
	"40006":{"x":0,"y":0,"w":62,"h":61},
	"40007":{"x":128,"y":0,"w":62,"h":59},
	"40008":{"x":128,"y":61,"w":62,"h":57},
	"40009":{"x":64,"y":0,"w":62,"h":60},
	"40010":{"x":192,"y":0,"w":62,"h":59},
	"40011":{"x":192,"y":61,"w":62,"h":57}
}}