{"mc":{
	"monster20018_2r":{
		"frameRate":14,
		"frames":[
			{"res":"20006","x":-129,"y":-214},
			{"res":"20007","x":-131,"y":-216},
			{"res":"20008","x":-134,"y":-211},
			{"res":"20009","x":-136,"y":-214},
			{"res":"20010","x":-135,"y":-215},
			{"res":"20011","x":-135,"y":-211}
		]
}},
"res":{
	"20006":{"x":2,"y":1368,"w":204,"h":278},
	"20007":{"x":2,"y":546,"w":208,"h":278},
	"20008":{"x":2,"y":1098,"w":208,"h":268},
	"20009":{"x":2,"y":276,"w":210,"h":268},
	"20010":{"x":2,"y":826,"w":208,"h":270},
	"20011":{"x":2,"y":2,"w":210,"h":272}
}}