{"mc":{
	"skill101_3":{
		"frameRate":10,
		"frames":[
			{"res":"00002","x":-256,"y":-256},
			{"res":"00003","x":-256,"y":-256},
			{"res":"00004","x":-256,"y":-256},
			{"res":"00005","x":-157,"y":-176},
			{"res":"00006","x":-152,"y":-176},
			{"res":"00007","x":-139,"y":-145},
			{"res":"00008","x":-125,"y":-144},
			{"res":"00009","x":-81,"y":-128},
			{"res":"00010","x":-75,"y":-126}
		]
}},
"res":{
	"00002":{"x":712,"y":184,"w":1,"h":1},
	"00003":{"x":712,"y":184,"w":1,"h":1},
	"00004":{"x":712,"y":184,"w":1,"h":1},
	"00005":{"x":354,"y":2,"w":356,"h":208},
	"00006":{"x":2,"y":2,"w":350,"h":210},
	"00007":{"x":712,"y":2,"w":326,"h":180},
	"00008":{"x":1040,"y":2,"w":306,"h":180},
	"00009":{"x":1348,"y":2,"w":252,"h":164},
	"00010":{"x":1602,"y":2,"w":250,"h":142}
}}